bmsdna/table_rendering/__init__.py
bmsdna/table_rendering/config.py
bmsdna/table_rendering/excel.py
bmsdna/table_rendering/html.py
bmsdna/table_rendering/md2excel.py
bmsdna/table_rendering/polars.py
bmsdna/table_rendering/spark.py
bmsdna/table_rendering/table_rendering.py
bmsdna_table_rendering-0.5.2.dist-info/METADATA
bmsdna_table_rendering-0.5.2.dist-info/WHEEL
bmsdna_table_rendering-0.5.2.dist-info/licenses/LICENSE
bmsdna_table_rendering-0.5.2.dist-info/RECORD
