Metadata-Version: 2.4
Name: bmsdna-table-rendering
Version: 0.5.2
Author-email: Adrian Ehrsam <adrian.ehrsam@bmsuisse.ch>
License-File: LICENSE
Requires-Python: ~=3.10
Requires-Dist: dominate<3,>=2.9.1
Requires-Dist: polars<2,>=1.0.0
Requires-Dist: pydantic>=1.10
Requires-Dist: xlsxwriter<4,>=3.2.0
Provides-Extra: spark
Requires-Dist: pyspark>=3.5.5; extra == 'spark'
